fabricengineer/py.typed
fabricengineer/api/auth.py
fabricengineer/api/utils.py
fabricengineer/api/fabric/client/fabric.py
fabricengineer/api/fabric/client/utils.py
fabricengineer/api/fabric/client/workspace.py
fabricengineer/api/fabric/workspace/__init__.py
fabricengineer/api/fabric/workspace/base.py
fabricengineer/api/fabric/workspace/create_pipeline.py
fabricengineer/api/fabric/workspace/workspace.py
fabricengineer/api/fabric/workspace/folder/__init__.py
fabricengineer/api/fabric/workspace/folder/folder.py
fabricengineer/api/fabric/workspace/items/__init__.py
fabricengineer/api/fabric/workspace/items/data_pipeline.py
fabricengineer/api/fabric/workspace/items/lakehouse.py
fabricengineer/api/fabric/workspace/items/notebook.py
fabricengineer/api/fabric/workspace/items/variable_library.py
fabricengineer/api/fabric/workspace/items/warehouse.py
fabricengineer/import_module/import_module.py
fabricengineer/logging/__init__.py
fabricengineer/logging/logger.py
fabricengineer/logging/timer.py
fabricengineer/setup/__init__.py
fabricengineer/transform/lakehouse.py
fabricengineer/transform/mlv/__init__.py
fabricengineer/transform/mlv/mlv.py
fabricengineer/transform/silver/__init__.py
fabricengineer/transform/silver/base.py
fabricengineer/transform/silver/insertonly.py
fabricengineer/transform/silver/scd2.py
fabricengineer/transform/silver/utils.py
fabricengineer_py-1.1.0.dist-info/METADATA
fabricengineer_py-1.1.0.dist-info/WHEEL
fabricengineer_py-1.1.0.dist-info/RECORD
