Metadata-Version: 2.4
Name: fabricengineer-py
Version: 1.1.0
Summary: Package for Fabric Engineers
Author-email: Enrico Goerlitz <private.email@gmail.com>
Requires-Python: >=3.11
Requires-Dist: delta-spark==3.2.0
Requires-Dist: dotenv>=0.9.9
Requires-Dist: pyspark==3.5.0
Requires-Dist: pytest>=8.4.1
Requires-Dist: requests>=2.32.4
